[
	
	
	{
		"appIcon": "https://play-lh.googleusercontent.com/RthOGgo-NSds0YHY92TMzQCfFcZtGpGfkRCmKmflTd5FAOxYPk_1RIRH9Jzj7g1ylWWK=s180-rw",
		"appName": "Game Booster 4x",
		"appDescription": "Game Booster 4x",
		"url": "https://play.google.com/store/apps/details?id=game.booster.gamebooster.fastgamebooster"
	},
	{
		"appIcon": "https://play-lh.googleusercontent.com/wqDSfkVJGW9M8oKPnhXWp8Wr0p5civedAp8mGqkY-6RIJViLnK1mfmLpdFcy9kUDwA=s180-rw",
		"appName": "Smart Cleaner Phone Booster",
		"appDescription": "Smart Cleaner Phone Booster",
		"url": "https://play.google.com/store/apps/details?id=com.superclean.fast.phone.clean.global"
	},
	{
		"appIcon": "https://play-lh.googleusercontent.com/dLSK8llj5LPla5es4TQPHJ2srcYDbuCVJZz6yydg1raU4dY6nq36p87tvOpMBL-eh-hi=s180-rw",
		"appName": "WhatsDelete Message and Photo",
		"appDescription": "WhatsDelete Message and Photo",
		"url": "https://play.google.com/store/apps/details?id=com.ahmed.whtasdelete.restoredeletedmessage.photo"
	},
	
	
]
